tablefaker/__init__.py
tablefaker/cli.py
tablefaker/config.py
tablefaker/llm_client.py
tablefaker/plugin_loader.py
tablefaker/relationships.py
tablefaker/semantic_model_metrics.py
tablefaker/semantic_view.py
tablefaker/tablefaker.py
tablefaker/util.py
tablefaker-1.8.0.dist-info/LICENSE
tablefaker-1.8.0.dist-info/METADATA
tablefaker-1.8.0.dist-info/WHEEL
tablefaker-1.8.0.dist-info/entry_points.txt
tablefaker-1.8.0.dist-info/top_level.txt
tablefaker-1.8.0.dist-info/RECORD
