Metadata-Version: 2.2
Name: tablefaker
Version: 1.8.0
Summary: A Python package to generate fake tabular data. Get data in pandas dataframe or export to Parquet, DeltaLake, Csv, Json, Excel or Sql
Home-page: https://github.com/necatiarslan/table-faker
Author: Necati Arslan
Author-email: necatia@gmail.com
License: Apache License 2.0
Project-URL: Documentation, https://github.com/necatiarslan/table-faker/blob/main/README.md
Project-URL: Source, https://github.com/necatiarslan/table-faker
Keywords: faker,fake data,tabular data,data generation,pandas,parquet,csv,json,excel,sqllite,delta lake
Classifier: Development Status :: 5 - Production/Stable
Classifier: Intended Audience :: Developers
Classifier: License :: OSI Approved :: Apache Software License
Classifier: Programming Language :: Python
Classifier: Programming Language :: Python :: 3
Classifier: Programming Language :: Python :: 3.7
Classifier: Programming Language :: Python :: 3.8
Classifier: Programming Language :: Python :: 3.9
Classifier: Programming Language :: Python :: 3.10
Classifier: Programming Language :: Python :: 3.11
Classifier: Programming Language :: Python :: 3.12
Classifier: Programming Language :: Python :: 3.13
Classifier: Programming Language :: Python :: 3.14
Classifier: Topic :: Software Development :: Libraries
Classifier: Topic :: Utilities
Classifier: Operating System :: OS Independent
Requires-Python: >=3.9
License-File: LICENSE
Requires-Dist: faker
Requires-Dist: pyyaml
Requires-Dist: pandas
Requires-Dist: openpyxl
Requires-Dist: fastparquet
Requires-Dist: psutil
Dynamic: author
Dynamic: author-email
Dynamic: classifier
Dynamic: description
Dynamic: description-content-type
Dynamic: home-page
Dynamic: keywords
Dynamic: license
Dynamic: project-url
Dynamic: requires-dist
Dynamic: requires-python
Dynamic: summary
